hishiryo/Hishiryo.py
hishiryo/__init__.py
hishiryo/_toolbox.py
hishiryo-0.0.3.dist-info/LICENSE
hishiryo-0.0.3.dist-info/METADATA
hishiryo-0.0.3.dist-info/WHEEL
hishiryo-0.0.3.dist-info/top_level.txt
hishiryo-0.0.3.dist-info/RECORD
