Metadata-Version: 2.1
Name: hishiryo
Version: 0.0.3
Summary: Render a dataset into a picture
Home-page: http://github.com/spriggancg/hishiryo
Author: Nicolas Boisseau
Author-email: spriggancg@gmail.com
License: UNKNOWN
Platform: UNKNOWN
Classifier: Development Status :: 4 - Beta
Classifier: License :: OSI Approved :: GNU General Public License v3 (GPLv3)
Classifier: Topic :: Artistic Software
Classifier: Operating System :: MacOS :: MacOS X
Requires-Python: >=3.6
License-File: LICENSE
Requires-Dist: pandas (<=1.3.5)
Requires-Dist: opencv-python
